[
    {
        "sport": "Soccer"
    },
    {
        "sport": "Basketball"
    },
    {
        "sport": "Cricket"
    },
    {
        "sport": "Field Hockey"
    },
    {
        "sport": "Tennis"
    },
    {
        "sport": "Volleyball"
    },
    {
        "sport": "Table Tennis"
    },
    {
        "sport": "Baseball"
    },
    {
        "sport": "American Football"
    },
    {
        "sport": "Badminton"
    },
    {
        "sport": "Rugby"
    },
    {
        "sport": "Golf"
    },
    {
        "sport": "Boxing"
    },
    {
        "sport": "Cycling"
    },
    {
        "sport": "Swimming"
    },
    {
        "sport": "Athletics (Track and Field)"
    },
    {
        "sport": "Formula 1 Racing"
    },
    {
        "sport": "Ice Hockey"
    },
    {
        "sport": "Handball"
    },
    {
        "sport": "Australian Rules Football"
    },
    {
        "sport": "Motorsport (General)"
    },
    {
        "sport": "Skiing"
    },
    {
        "sport": "Skating"
    },
    {
        "sport": "Gymnastics"
    },
    {
        "sport": "Wrestling"
    },
    {
        "sport": "Martial Arts (General)"
    },
    {
        "sport": "Judo"
    },
    {
        "sport": "Karate"
    },
    {
        "sport": "Taekwondo"
    },
    {
        "sport": "MMA (Mixed Martial Arts)"
    },
    {
        "sport": "Netball"
    },
    {
        "sport": "Squash"
    },
    {
        "sport": "Racquetball"
    },
    {
        "sport": "Lacrosse"
    },
    {
        "sport": "Water Polo"
    },
    {
        "sport": "Rowing"
    },
    {
        "sport": "Sailing"
    },
    {
        "sport": "Canoeing/Kayaking"
    },
    {
        "sport": "Archery"
    },
    {
        "sport": "Shooting"
    },
    {
        "sport": "Weightlifting"
    },
    {
        "sport": "Equestrian Sports"
    },
    {
        "sport": "Polo"
    },
    {
        "sport": "Curling"
    },
    {
        "sport": "Darts"
    },
    {
        "sport": "Snooker/Pool"
    },
    {
        "sport": "Chess"
    },
    {
        "sport": "Esports (Competitive Video Gaming)"
    },
    {
        "sport": "Triathlon"
    },
    {
        "sport": "Bowling"
    }
]